{
  "version": "1.3.113",
  "description": "winghostty is a Windows terminal emulator that reuses Ghostty's terminal core under a native Win32 front end.",
  "homepage": "https://github.com/amanthanvi/winghostty",
  "license": "MIT",
  "architecture": {
    "64bit": {
      "url": "https://github.com/amanthanvi/winghostty/releases/download/v1.3.113/winghostty-1.3.113-windows-x64-portable.zip",
      "hash": "99535d19251474de752dfb7207e7279eba47838411c17a2a186d63981810f462"
    },
    "arm64": {
      "url": "https://github.com/amanthanvi/winghostty/releases/download/v1.3.113/winghostty-1.3.113-windows-arm64-portable.zip",
      "hash": "5b2cc7233d394a3b9b649faef608b6e0a3e91a230eb8e23f8351a9bbac54fa04"
    }
  },
  "extract_dir": "winghostty",
  "bin": "winghostty.exe"
}
